gip/__init__.py
gip/exceptions.py
gip/logger.py
gip/shell.py
gip/util.py
gip/command/__init__.py
gip/command/install.py
gip/model/__init__.py
gip/model/scheme.py
gip/sources/__init__.py
gip/sources/base.py
gip/sources/github.py
gip/sources/gitlab.py
gip-0.1.5.dist-info/AUTHORS
gip-0.1.5.dist-info/METADATA
gip-0.1.5.dist-info/WHEEL
gip-0.1.5.dist-info/entry_points.txt
gip-0.1.5.dist-info/pbr.json
gip-0.1.5.dist-info/top_level.txt
gip-0.1.5.dist-info/RECORD
