Metadata-Version: 2.1
Name: gip
Version: 0.1.5
Summary: Gip is a language agnostic dependency manager which uses API calls to pull repositories.
Home-page: UNKNOWN
Maintainer: Intermax Cloudsourcing
Maintainer-email: wilmaro@intermax.nl
License: UNKNOWN
Project-URL: Bug Tracker, https://github.com/Intermax-Cloudsourcing/gip/issues
Project-URL: Source Code, https://github.com/Intermax-Cloudsourcing/gip
Platform: UNKNOWN
Classifier: Development Status :: 4 - Beta
Classifier: Environment :: Console
Classifier: Intended Audience :: Developers
Classifier: Intended Audience :: Information Technology
Classifier: Intended Audience :: System Administrators
Classifier: License :: OSI Approved :: MIT License
Classifier: Natural Language :: English
Classifier: Operating System :: OS Independent
Classifier: Programming Language :: Python :: 3
Classifier: Topic :: System :: Systems Administration
Classifier: Topic :: Utilities
Requires-Dist: pbr (==5.2.1)
Requires-Dist: cerberus (==1.3.1)
Requires-Dist: click (==7.0)
Requires-Dist: colorama (==0.4.1)
Requires-Dist: pyyaml (==5.1)
Requires-Dist: python-gitlab (==1.8.0)
Requires-Dist: github3.py (==1.3.0)
Provides-Extra: docs
Requires-Dist: Sphinx ; extra == 'docs'
